mcp_server_redis/__init__.py
mcp_server_redis/__main__.py
mcp_server_redis/py.typed
mcp_server_redis/server.py
mcp_server_redis-0.1.1.dist-info/METADATA
mcp_server_redis-0.1.1.dist-info/WHEEL
mcp_server_redis-0.1.1.dist-info/entry_points.txt
mcp_server_redis-0.1.1.dist-info/RECORD
