Metadata-Version: 2.4
Name: mcp-server-redis
Version: 0.1.1
Summary: Add your description here
Author-email: truskovskiyk <truskovskiyk@gmail.com>
Requires-Python: >=3.12
Requires-Dist: mcp[cli]>=1.4.1
Requires-Dist: pydantic-settings>=2.8.1
Requires-Dist: redis>=5.2.1
